botapp
