Metadata-Version: 2.4
Name: botapp
Version: 0.2.13
Summary: Pacote Django para gerenciamento de bots e tarefas de RPA
Author: Ben-Hur P. B. Santos
Author-email: botlorien@gmail.com
License: MIT
Classifier: Framework :: Django
Classifier: Programming Language :: Python :: 3
Classifier: License :: OSI Approved :: MIT License
Classifier: Operating System :: OS Independent
Requires-Python: >=3.8
License-File: LICENSE
Requires-Dist: Django>=3.2
Requires-Dist: psycopg2-binary>=2.9.10
Requires-Dist: django-admin-rangefilter
Requires-Dist: openpyxl
Requires-Dist: python-dotenv>=1.0.0
Requires-Dist: xhtml2pdf>=0.2.5
Requires-Dist: whitenoise
Requires-Dist: djangorestframework
Requires-Dist: requests
Requires-Dist: django-ratelimit
Dynamic: author
Dynamic: author-email
Dynamic: classifier
Dynamic: description
Dynamic: description-content-type
Dynamic: license
Dynamic: license-file
Dynamic: requires-dist
Dynamic: requires-python
Dynamic: summary
